pylogconfig/__init__.py
pylogconfig/pylogconfig.py
pylogconfig-0.1.0a0.dist-info/LICENSE
pylogconfig-0.1.0a0.dist-info/WHEEL
pylogconfig-0.1.0a0.dist-info/METADATA
pylogconfig-0.1.0a0.dist-info/RECORD
