Metadata-Version: 2.1
Name: pylogconfig
Version: 0.1.0a0
Summary: Easily configure Python logger with configuration files.
License: MIT
Author: RemyLau
Author-email: remylau961@gmail.com
Requires-Python: >=3.7,<4.0
Classifier: License :: OSI Approved :: MIT License
Classifier: Programming Language :: Python :: 3
Classifier: Programming Language :: Python :: 3.10
Classifier: Programming Language :: Python :: 3.7
Classifier: Programming Language :: Python :: 3.8
Classifier: Programming Language :: Python :: 3.9
